pyepggrab/__about__.py
pyepggrab/__init__.py
pyepggrab/args.py
pyepggrab/ask.py
pyepggrab/configbase.py
pyepggrab/configmanager.py
pyepggrab/log.py
pyepggrab/pyepggrab.py
pyepggrab/utils.py
pyepggrab/xmltv.py
pyepggrab/xmlwriter.py
pyepggrab/grabbers/__init__.py
pyepggrab/grabbers/hu_porthu/__init__.py
pyepggrab/grabbers/hu_porthu/catmap.py
pyepggrab/grabbers/hu_porthu/config.py
pyepggrab/grabbers/hu_porthu/hu_porthu.py
pyepggrab/grabbers/hu_porthu/request_proc.py
pyepggrab/grabbers/hu_porthu/use_ip_adapter.py
pyepggrab/grabbers/hu_porthu/utils.py
pyepggrab/grabbers/hu_porthu/xml_utils.py
pyepggrab/resources/xmltv.dtd
pyepggrab-0.3.3.dist-info/METADATA
pyepggrab-0.3.3.dist-info/WHEEL
pyepggrab-0.3.3.dist-info/entry_points.txt
pyepggrab-0.3.3.dist-info/licenses/LICENSE.txt
pyepggrab-0.3.3.dist-info/RECORD
