Metadata-Version: 2.4
Name: pyepggrab
Version: 0.3.3
Summary: Drop in replacement/extension to xmltv grabbers
Project-URL: Documentation, https://github.com/pyepggrab/pyepggrab#readme
Project-URL: Issues, https://github.com/pyepggrab/pyepggrab/issues
Project-URL: Source, https://github.com/pyepggrab/pyepggrab
License-Expression: MIT
License-File: LICENSE.txt
Keywords: XMLTV,epg,tv
Classifier: Development Status :: 4 - Beta
Classifier: Programming Language :: Python
Classifier: Programming Language :: Python :: 3.8
Classifier: Programming Language :: Python :: 3.9
Classifier: Programming Language :: Python :: 3.10
Classifier: Programming Language :: Python :: 3.11
Classifier: Programming Language :: Python :: 3.12
Classifier: Programming Language :: Python :: 3.13
Requires-Python: >=3.8
Requires-Dist: backports-zoneinfo; python_version < '3.9'
Requires-Dist: beautifulsoup4
Requires-Dist: dnspython
Requires-Dist: extruct
Requires-Dist: lxml
Requires-Dist: requests
Requires-Dist: roman
Requires-Dist: typing-extensions>=4.4; python_version < '3.12'
Requires-Dist: tzdata
Requires-Dist: urllib3
Provides-Extra: develop
Requires-Dist: black; extra == 'develop'
Requires-Dist: hatch; extra == 'develop'
Requires-Dist: mypy; extra == 'develop'
Requires-Dist: ruff; extra == 'develop'
